[
  "周一更新:",
  { "title": "我与机器子", "part": "第27集 new" },
  { "title": "再得一胜！", "part": "第13集(完结)" },
  { "title": "致不灭的你 第二季", "part": "第20集(完结)" },
  { "title": "飙速宅男 第五季", "part": "第25集(完结)" },
  { "title": "High Card", "part": "第12集(完结)" },
  { "title": "吸血鬼马上死 第二季", "part": "第12集(完结)" },
  { "title": "黄金神威 第四季", "part": "第47集" },
  { "title": "机战少女 Alice Expansion", "part": "第11集" },
  { "title": "公爵的契约未婚妻", "part": "第10集" },
  { "title": "熊熊勇闯异世界 第二季", "part": "第11集" },
  { "title": "带着智能手机闯荡异世界 第二季", "part": "第11集" },
  "最近更新",
  { "title": "宝可梦 地平线 莉可与罗伊踏上旅途", "part": "第11集" },
  { "title": "我与机器子", "part": "第27集" },
  { "title": "我家的英雄", "part": "第12集" },
  { "title": "魔法少女毁灭者", "part": "第11集" },
  {
    "title": "转生贵族的异世界冒险录～不知自重的诸神的使徒～",
    "part": "第12集"
  },
  { "title": "黑色五叶草 魔法帝之剑", "part": "[全集]" },
  { "title": "虫王战队超王者", "part": "第15集" },
  { "title": "假面骑士极狐", "part": "第40集" },
  { "title": "地狱乐", "part": "第11集" },
  { "title": "斗罗大陆4终极斗罗 动态漫", "part": "第34集" },
  { "title": "九天玄帝诀", "part": "第118集" },
  { "title": "无上神帝", "part": "第262集" },
  { "title": "万古神话", "part": "第60集" },
  { "title": "独步逍遥", "part": "第300集" },
  { "title": "逆天至尊", "part": "第185集" },
  { "title": "万界仙踪 第五季", "part": "第363集" },
  { "title": "星辰变 第五季", "part": "第16集" },
  { "title": "丹道宗师", "part": "第15集" },
  { "title": "黑色五叶草 魔法帝之剑", "part": "[全集]" },
  { "title": "铃芽之旅", "part": "[全集]" },
  { "title": "镜之孤城", "part": "[全集]" },
  { "title": "我们的黎明", "part": "[全集]" },
  { "title": "UN-GO episode: 0 因果论", "part": "[全集]" },
  { "title": "通往夏天的隧道，再见的出口", "part": "[全集]" },
  { "title": "刀剑神域 进击篇 黯淡黄昏的谐谑曲", "part": "[全集]" },
  { "title": "致我深爱的每个你", "part": "[全集]" },
  { "title": "擅长捉弄的高木同学剧场版", "part": "[全集]" },
  {
    "title": "转生贵族的异世界冒险录～不知自重的诸神的使徒～",
    "part": "第12集"
  },
  { "title": "女神的露天咖啡厅", "part": "第11集" },
  { "title": "六道的恶女们", "part": "第11集" },
  { "title": "带着智能手机闯荡异世界 第二季", "part": "23:30 第11集" },
  { "title": "想要成为影之实力者！ 第二季", "part": "PV" },
  { "title": "最强阴阳师的异世界转生记", "part": "第13集(完结)" },
  { "title": "真・进化果实～不知不觉踏上胜利的人生～", "part": "第12集(完结)" },
  { "title": "被神捡到的男人 第二季", "part": "第12集(完结)" },
  { "title": "期待在地下城邂逅有错吗 第四季", "part": "第22集(完结)" },
  { "title": "星辰变 第五季", "part": "第16集" },
  { "title": "黑色五叶草 魔法帝之剑", "part": "[全集]" },
  { "title": "妖神记 第五季", "part": "第304集" },
  { "title": "斗罗大陆", "part": "第264集" },
  { "title": "一品高手 动态漫", "part": "第21集" },
  { "title": "末世超级系统 动态漫", "part": "第42集" },
  { "title": "万古龙神 动态漫", "part": "第29集" },
  { "title": "冰火魔厨", "part": "第62集" },
  { "title": "我靠bug上王者 动态漫", "part": "第25集" }
]
